year_progress/__init__.py
year_progress-2.0.25.dist-info/METADATA
year_progress-2.0.25.dist-info/WHEEL
year_progress-2.0.25.dist-info/licenses/LICENSE
year_progress-2.0.25.dist-info/RECORD
